{
  "properties": {
    "id": {
      "type": "text",
      "index": false
    },
    "level": {
      "type": "long",
      "index": false
    },
    "zip_codes": {
      "type": "text",
      "index_options": "docs",
      "analyzer": "word",
      "copy_to": "full_label"
    },
    "coord": {
      "type": "geo_point"
    },
    "approx_coord": {
      "type": "geo_shape"
    },
    "label": {
      "type": "text",
      "analyzer": "autocomplete",
      "search_analyzer": "autocomplete_search",
      "copy_to": "full_label"
    },
    "full_label": {
      "type": "text",
      "analyzer": "prefix_elision"
    },
    "weight": {
      "type": "double"
    },
    "zone_type": {
      "type": "text",
      "index": false
    },
    "indexed_at": {
      "type": "date"
    }
  }
}
